{"cameraMode":{"drawMode":0,"name":"Shaded","section":"Shading Mode"},"sceneLighting":false,"audioPlay":false,"sceneViewState":{"showFog":true,"showMaterialUpdate":false,"showSkybox":false,"showFlares":true,"showImageEffects":true,"showParticleSystems":true,"showVisualEffectGraphs":true,"m_FxEnabled":true},"in2DMode":false,"pivot":{"x":24.638042449951173,"y":4.578031539916992,"z":-19.96213722229004},"rotation":{"x":0.3182179629802704,"y":-0.02843480184674263,"z":0.00954955443739891,"w":0.9475436210632324},"size":7.478487968444824,"orthographic":false}